llm_templates_fsspec.py
llm_templates_fsspec-0.1.1.dist-info/METADATA
llm_templates_fsspec-0.1.1.dist-info/WHEEL
llm_templates_fsspec-0.1.1.dist-info/entry_points.txt
llm_templates_fsspec-0.1.1.dist-info/top_level.txt
llm_templates_fsspec-0.1.1.dist-info/RECORD
