Metadata-Version: 2.4
Name: llm-templates-fsspec
Version: 0.1.1
Summary: Load LLM templates from local paths and cloud storage (S3, GCS, Azure) using any supported fsspec URL scheme.
Author: Mario-César Señoranis
License: Apache-2.0
Project-URL: Homepage, https://github.com/mariocesar/llm-templates-fsspec
Project-URL: Changelog, https://github.com/mariocesar/llm-templates-fsspec/releases
Project-URL: Issues, https://github.com/mariocesar/llm-templates-fsspec/issues
Project-URL: CI, https://github.com/mariocesar/llm-templates-fsspec/actions
Classifier: License :: OSI Approved :: Apache Software License
Requires-Python: >=3.11
Requires-Dist: fsspec>=2025.3.2
Requires-Dist: llm>=0.24
Provides-Extra: test
Requires-Dist: pytest; extra == "test"
Requires-Dist: pytest-httpx; extra == "test"
